README.md
setup.py
bin/machsmt
machsmt/__init__.py
machsmt/machsmt.py
machsmt.egg-info/PKG-INFO
machsmt.egg-info/SOURCES.txt
machsmt.egg-info/dependency_links.txt
machsmt.egg-info/top_level.txt
machsmt/benchmark/__init__.py
machsmt/benchmark/benchmark.py
machsmt/benchmark/tokenize_sexpr.py
machsmt/config/__init__.py
machsmt/config/config.py
machsmt/database/__init__.py
machsmt/database/db.py
machsmt/ex/__init__.py
machsmt/ex/ex.py
machsmt/exceptions/__init__.py
machsmt/exceptions/exceptions.py
machsmt/features/__init__.py
machsmt/features/arrays.py
machsmt/features/bv.py
machsmt/features/extra.py
machsmt/features/fp.py
machsmt/features/integer.py
machsmt/features/quantifiers.py
machsmt/features/real.py
machsmt/features/string.py
machsmt/features/uf.py
machsmt/ml/__init__.py
machsmt/ml/mach_scikit.py
machsmt/ml/mach_torch.py
machsmt/ml/mach_xgboost.py
machsmt/ml/mlp.py
machsmt/ml/model_maker.py
machsmt/selectors/__init__.py
machsmt/selectors/base.py
machsmt/selectors/ehm.py
machsmt/selectors/greedy.py
machsmt/selectors/pwc.py
machsmt/selectors/random.py
machsmt/smtlib/__init__.py
machsmt/smtlib/constructs.py
machsmt/smtlib/util.py
machsmt/solver/__init__.py
machsmt/solver/solver.py
machsmt/util/__init__.py
machsmt/util/logger.py
machsmt/util/util.py